mumailer/__init__.py
mumailer/attachment.py
mumailer/command_line_options.py
mumailer/connection.py
mumailer/constants.py
mumailer/encryption.py
mumailer/header.py
mumailer/message.py
mumailer/profile_message.py
mumailer/profile_smtp.py
mumailer/recipient.py
mumailer/yaml_profile.py
mumailer/samples/main.py
mumailer/samples/profile_smtp.py
mumailer/samples/simple_ssl.py
mumailer/samples/simple_tls.py
MuMailer-0.5.0.dist-info/LICENSE
MuMailer-0.5.0.dist-info/METADATA
MuMailer-0.5.0.dist-info/WHEEL
MuMailer-0.5.0.dist-info/entry_points.txt
MuMailer-0.5.0.dist-info/top_level.txt
MuMailer-0.5.0.dist-info/RECORD
