Metadata-Version: 2.1
Name: MuMailer
Version: 0.5.0
Summary: Simple mailer agent using SMTP
Home-page: http://www.muflone.com/mumailer/
Author: Fabio Castelli
Author-email: muflone@muflone.com
License: GPLv3+
Classifier: Development Status :: 1 - Planning
Classifier: Intended Audience :: Developers
Classifier: License :: OSI Approved :: GNU General Public License v3 or later (GPLv3+)
Classifier: Operating System :: OS Independent
Classifier: Programming Language :: Python :: 3
Classifier: Programming Language :: Python :: 3.9
Classifier: Programming Language :: Python :: 3.10
Classifier: Programming Language :: Python :: 3.11
Classifier: Topic :: Software Development :: Libraries :: Python Modules
License-File: LICENSE
Requires-Dist: pyyaml ==6.0.1
